{
  "team": "Zambia",
  "players": [
    {
      "name": "Lawrence Mulenga",
      "summary": "Tresford Lawrence Mulenga is a Zambian professional footballer who plays as a goalkeeper for Power Dynamos and the Zambia national team.",
      "page_url": "https://en.wikipedia.org/wiki/Lawrence_Mulenga",
      "thumbnail": null,
      "wiki_url": "https://en.wikipedia.org/wiki/Lawrence_Mulenga",
      "position": "1GK",
      "date_of_birth": "( 1998-08-21 ) 21 August 1998 (age 27)",
      "caps": "18",
      "goals": "0",
      "club": "Power Dynamos"
    },
    {
      "name": "Frankie Musonda",
      "summary": "Frankie Chisenga Musonda is a professional footballer who plays as a defender. Born in England, he plays for the Zambia national team.",
      "page_url": "https://en.wikipedia.org/wiki/Frankie_Musonda",
      "thumbnail": null,
      "wiki_url": "https://en.wikipedia.org/wiki/Frankie_Musonda",
      "position": "2DF",
      "date_of_birth": "( 1997-12-12 ) 12 December 1997 (age 28)",
      "caps": "20",
      "goals": "1",
      "club": "Bahrain SC"
    },
    {
      "name": "Lubambo Musonda",
      "summary": "Lubambo Musonda is a Zambian professional footballer who plays as a left winger for German 2. Bundesliga club 1. FC Magdeburg and the Zambia national team.",
      "page_url": "https://en.wikipedia.org/wiki/Lubambo_Musonda",
      "thumbnail": null,
      "wiki_url": "https://en.wikipedia.org/wiki/Lubambo_Musonda",
      "position": "2DF",
      "date_of_birth": "( 1995-03-01 ) 1 March 1995 (age 30)",
      "caps": "59",
      "goals": "2",
      "club": "1. FC Magdeburg"
    },
    {
      "name": "Stoppila Sunzu",
      "summary": "Stoppila Sunzu, also known as Stophira Sunzu, is a Zambian professional footballer who plays as a centre-back for Chinese Super League club Changchun Yatai. He scored the winning penalty kick for Zambia in the 2012 Africa Cup of Nations final.",
      "page_url": "https://en.wikipedia.org/wiki/Stoppila_Sunzu",
      "thumbnail": "https://upload.wikimedia.org/wikipedia/commons/thumb/8/8c/Stoppila_Sunzu_May_2017.jpg/330px-Stoppila_Sunzu_May_2017.jpg",
      "wiki_url": "https://en.wikipedia.org/wiki/Stoppila_Sunzu",
      "position": "2DF",
      "date_of_birth": "( 1989-06-22 ) 22 June 1989 (age 36)",
      "caps": "80",
      "goals": "5",
      "club": "Changchun Yatai"
    },
    {
      "name": "Kabaso Chongo",
      "summary": "Kabaso Chongo is a Zambian professional footballer who plays as a defender for Linafoot club TP Mazembe.",
      "page_url": "https://en.wikipedia.org/wiki/Kabaso_Chongo",
      "thumbnail": null,
      "wiki_url": "https://en.wikipedia.org/wiki/Kabaso_Chongo",
      "position": "2DF",
      "date_of_birth": "( 1992-02-11 ) 11 February 1992 (age 33)",
      "caps": "44",
      "goals": "1",
      "club": "ZESCO United"
    },
    {
      "name": "Dominic Chanda",
      "summary": "Dominic Chanda is a Zambian professional footballer who plays as a defender for Kabwe Warriors and the Zambia national football team.",
      "page_url": "https://en.wikipedia.org/wiki/Dominic_Chanda",
      "thumbnail": null,
      "wiki_url": "https://en.wikipedia.org/wiki/Dominic_Chanda",
      "position": "2DF",
      "date_of_birth": "( 1996-02-26 ) 26 February 1996 (age 29)",
      "caps": "28",
      "goals": "1",
      "club": "Power Dynamos"
    },
    {
      "name": "David Hamansenya",
      "summary": "David Hamansenya is a Zambian professional footballer who plays as a left-back for the Segunda División club Leganés and the Zambia national team.",
      "page_url": "https://en.wikipedia.org/wiki/David_Hamansenya",
      "thumbnail": null,
      "wiki_url": "https://en.wikipedia.org/wiki/David_Hamansenya",
      "position": "2DF",
      "date_of_birth": "( 2007-06-24 ) 24 June 2007 (age 18)",
      "caps": "4",
      "goals": "0",
      "club": "Leganés"
    },
    {
      "name": "Gift Mphande",
      "summary": "Gift Prosper Mphande is a Zambian professional footballer who plays as a centre-back for Zambian club ZESCO United and the Zambia national team.",
      "page_url": "https://en.wikipedia.org/wiki/Gift_Mphande",
      "thumbnail": null,
      "wiki_url": "https://en.wikipedia.org/wiki/Gift_Mphande",
      "position": "2DF",
      "date_of_birth": "( 2003-11-19 ) 19 November 2003 (age 22)",
      "caps": "13",
      "goals": "0",
      "club": "ZESCO United"
    },
    {
      "name": "Miguel Chaiwa",
      "summary": "Miguel Changa Chaiwa is a Zambian professional footballer who plays as a defensive midfielder for Scottish Premiership club Hibernian and the Zambia national team.",
      "page_url": "https://en.wikipedia.org/wiki/Miguel_Chaiwa",
      "thumbnail": null,
      "wiki_url": "https://en.wikipedia.org/wiki/Miguel_Chaiwa",
      "position": "3MF",
      "date_of_birth": "( 2004-06-07 ) 7 June 2004 (age 21)",
      "caps": "16",
      "goals": "0",
      "club": "Hibernian"
    },
    {
      "name": "Benson Sakala",
      "summary": "Benson Sakala is a Zambian professional footballer who plays as a midfielder for Bohemians 1905 and the Zambia national team where he has been appointed captain ahead of 2023 AFCON qualifiers.",
      "page_url": "https://en.wikipedia.org/wiki/Benson_Sakala",
      "thumbnail": null,
      "wiki_url": "https://en.wikipedia.org/wiki/Benson_Sakala",
      "position": "3MF",
      "date_of_birth": "( 1996-09-12 ) 12 September 1996 (age 29)",
      "caps": "37",
      "goals": "0",
      "club": "Bohemians 1905"
    },
    {
      "name": "Kings Kangwa",
      "summary": "Kings Kangwa is a Zambian professional footballer who plays as a midfielder for Israeli Premier League club Hapoel Be'er Sheva and the Zambia national team.",
      "page_url": "https://en.wikipedia.org/wiki/Kings_Kangwa",
      "thumbnail": "https://upload.wikimedia.org/wikipedia/commons/c/c1/Kings_Kangwa_2022.jpg",
      "wiki_url": "https://en.wikipedia.org/wiki/Kings_Kangwa",
      "position": "3MF",
      "date_of_birth": "( 1999-04-06 ) 6 April 1999 (age 26)",
      "caps": "43",
      "goals": "7",
      "club": "Hapoel Be'er Sheva"
    },
    {
      "name": "Joseph Liteta",
      "summary": "Joseph Liteta is a Zambian professional footballer who plays as a midfielder for Cagliari Primavera U20 team of Italian team Cagliari.",
      "page_url": "https://en.wikipedia.org/wiki/Joseph_Liteta",
      "thumbnail": null,
      "wiki_url": "https://en.wikipedia.org/wiki/Joseph_Liteta",
      "position": "3MF",
      "date_of_birth": "( 2006-02-22 ) 22 February 2006 (age 19)",
      "caps": "1",
      "goals": "0",
      "club": "Cagliari"
    },
    {
      "name": "Jack Lahne",
      "summary": "Jack Daniel Kalichi Lahne is a professional footballer who plays as striker for 2. Liga club Austria Lustenau. A former youth international for Sweden, he plays for the Zambia national team.",
      "page_url": "https://en.wikipedia.org/wiki/Jack_Lahne",
      "thumbnail": null,
      "wiki_url": "https://en.wikipedia.org/wiki/Jack_Lahne",
      "position": "4FW",
      "date_of_birth": "( 2001-10-24 ) 24 October 2001 (age 24)",
      "caps": "4",
      "goals": "1",
      "club": "Austria Lustenau"
    },
    {
      "name": "Lameck Banda",
      "summary": "Lameck Banda is a Zambian professional footballer who plays as a left winger for Serie A club Lecce and the Zambia national team.",
      "page_url": "https://en.wikipedia.org/wiki/Lameck_Banda",
      "thumbnail": "https://upload.wikimedia.org/wikipedia/commons/thumb/f/fc/Lameck_Banda_2019.jpg/330px-Lameck_Banda_2019.jpg",
      "wiki_url": "https://en.wikipedia.org/wiki/Lameck_Banda",
      "position": "4FW",
      "date_of_birth": "( 2001-01-29 ) 29 January 2001 (age 24)",
      "caps": "22",
      "goals": "3",
      "club": "Lecce"
    },
    {
      "name": "Fashion Sakala",
      "summary": "Junior Fashion Sakala is a Zambian professional footballer who plays as a forward for Saudi Pro League club Al-Fayha and the Zambia national team.",
      "page_url": "https://en.wikipedia.org/wiki/Fashion_Sakala",
      "thumbnail": "https://upload.wikimedia.org/wikipedia/commons/thumb/e/e3/Fashion_Sakala_2017.jpg/330px-Fashion_Sakala_2017.jpg",
      "wiki_url": "https://en.wikipedia.org/wiki/Fashion_Sakala",
      "position": "4FW",
      "date_of_birth": "( 1997-03-14 ) 14 March 1997 (age 28)",
      "caps": "38",
      "goals": "11",
      "club": "Al-Fayha"
    },
    {
      "name": "Kennedy Musonda",
      "summary": "Kennedy Musonda is a Zambian professional footballer who plays as a striker for Liga Leumit club Hapoel Ramat Gan and the Zambia national team.",
      "page_url": "https://en.wikipedia.org/wiki/Kennedy_Musonda",
      "thumbnail": null,
      "wiki_url": "https://en.wikipedia.org/wiki/Kennedy_Musonda",
      "position": "4FW",
      "date_of_birth": "( 1994-12-28 ) 28 December 1994 (age 31)",
      "caps": "20",
      "goals": "4",
      "club": "Hapoel Ramat Gan"
    },
    {
      "name": "Patson Daka",
      "summary": "Patson Daka is a Zambian professional footballer who plays as a striker for EFL Championship club Leicester City and the Zambia national team.",
      "page_url": "https://en.wikipedia.org/wiki/Patson_Daka",
      "thumbnail": "https://upload.wikimedia.org/wikipedia/commons/thumb/7/75/FC_RB_Salzburg_versus_CSKA_Sofia_%28Testspiel_3._Juli_2019%29_18.jpg/330px-FC_RB_Salzburg_versus_CSKA_Sofia_%28Testspiel_3._Juli_2019%29_18.jpg",
      "wiki_url": "https://en.wikipedia.org/wiki/Patson_Daka",
      "position": "4FW",
      "date_of_birth": "( 1998-10-09 ) 9 October 1998 (age 27)",
      "caps": "46",
      "goals": "21",
      "club": "Leicester City"
    }
  ]
}